LICENSE
people/__init__.py
people/admin.py
people/apps.py
people/cms_apps.py
people/cms_plugins.py
people/migrations/0001_initial.py
people/migrations/0002_auto_20191219_1343.py
people/migrations/0003_auto_20191219_1604.py
people/migrations/0004_auto_20200219_0949.py
people/migrations/0004_auto_20200219_0949.py.e320e942fc8c5685ceac7ec256cc0bb1.py
people/migrations/0005_person_tags.py
people/migrations/0006_auto_20200219_1032.py
people/migrations/0007_auto_20200219_1659.py
people/migrations/0008_auto_20200224_1217.py
people/migrations/0009_auto_20200227_1447.py
people/migrations/0009_auto_20200302_1052.py
people/migrations/0010_merge_20200303_0912.py
people/migrations/0011_auto_20200311_1540.py
people/migrations/0012_auto_20200401_1046.py
people/migrations/0013_auto_20200409_1422.py
people/migrations/0014_person_programme.py
people/migrations/0015_auto_20200518_1315.py
people/migrations/0016_person_organisation_role.py
people/migrations/0017_auto_20200602_1355.py
people/migrations/0018_person_popup_text.py
people/migrations/0019_strip_classes.py
people/migrations/0020_add_ordering_option.py
people/migrations/0021_add_container_plugin.py
people/migrations/0022_person_quote.py
people/migrations/__init__.py
people/models.py
people/templates/base.html
people/templates/people/index.html
people/templates/people/plugin.html
people/tests/__init__.py
people/tests/conftest.py
people/tests/test_cms_apps.py
people/tests/test_cms_plugins.py
people/tests/test_models.py
people/tests/test_views.py
people/tests/urls.py
people/urls.py
people/views.py
giant_people-0.5.0.dist-info/LICENSE
giant_people-0.5.0.dist-info/WHEEL
giant_people-0.5.0.dist-info/METADATA
giant_people-0.5.0.dist-info/RECORD
