Metadata-Version: 2.1
Name: giant-people
Version: 0.5.0
Summary: A small reusable package that adds a People app to a project
Home-page: https://github.com/giantmade/giant-people
License: MIT
Keywords: people,app
Author: Will-Hoey
Author-email: will.hoey@giantmade.com
Requires-Python: >=3.6,<4.0
Classifier: Environment :: Console
Classifier: License :: OSI Approved :: MIT License
Classifier: Operating System :: OS Independent
Classifier: Programming Language :: Python :: 3
Classifier: Programming Language :: Python :: 3.10
Classifier: Programming Language :: Python :: 3.6
Classifier: Programming Language :: Python :: 3.7
Classifier: Programming Language :: Python :: 3.8
Classifier: Programming Language :: Python :: 3.9
Classifier: Topic :: Software Development :: Documentation
Classifier: Topic :: Software Development :: Libraries :: Python Modules
Requires-Dist: django-admin-sortable2
Requires-Dist: django-filer
Requires-Dist: django-polymorphic (<=3.0.0)
Requires-Dist: giant-mixins
Requires-Dist: six (>=1.16.0,<2.0.0)
Project-URL: Repository, https://github.com/giantmade/giant-people
